oxymetag/__init__.py
oxymetag/cli.py
oxymetag/core.py
oxymetag/utils.py
oxymetag/data/.DS_Store
oxymetag/data/Oxygen_pfams.csv
oxymetag/data/VTML20.out
oxymetag/data/nucleotide.out
oxymetag/data/oxygen_model.rds
oxymetag/data/oxymetag_pfams.dmnd
oxymetag/data/oxymetag_pfams_n117.dmnd
oxymetag/data/oxymetag_pfams_n117_db
oxymetag/data/oxymetag_pfams_n117_db.dbtype
oxymetag/data/oxymetag_pfams_n117_db.index
oxymetag/data/oxymetag_pfams_n117_db.lookup
oxymetag/data/oxymetag_pfams_n117_db.source
oxymetag/data/oxymetag_pfams_n117_db_h
oxymetag/data/oxymetag_pfams_n117_db_h.dbtype
oxymetag/data/oxymetag_pfams_n117_db_h.index
oxymetag/data/pfam_headers_table.txt
oxymetag/data/pfam_lengths.tsv
oxymetag/scripts/predict_oxygen.R
tests/__init__.py
oxymetag-1.1.2.dist-info/LICENSE
oxymetag-1.1.2.dist-info/METADATA
oxymetag-1.1.2.dist-info/WHEEL
oxymetag-1.1.2.dist-info/entry_points.txt
oxymetag-1.1.2.dist-info/top_level.txt
oxymetag-1.1.2.dist-info/RECORD
