Metadata-Version: 2.1
Name: oxymetag
Version: 1.1.2
Summary: Oxygen metabolism profiling from metagenomic data
Home-page: https://github.com/cliffbueno/oxymetag
Author: Clifton P. Bueno de Mesquita
Author-email: cliff.buenodemesquita@colorado.edu
Classifier: Development Status :: 4 - Beta
Classifier: Intended Audience :: Science/Research
Classifier: License :: OSI Approved :: GNU General Public License v3 (GPLv3)
Classifier: Operating System :: OS Independent
Classifier: Programming Language :: Python :: 3
Classifier: Programming Language :: Python :: 3.7
Classifier: Programming Language :: Python :: 3.8
Classifier: Programming Language :: Python :: 3.9
Classifier: Programming Language :: Python :: 3.10
Classifier: Topic :: Scientific/Engineering :: Bio-Informatics
Requires-Python: >=3.7
License-File: LICENSE
Requires-Dist: pandas >=1.3.0
Requires-Dist: numpy >=1.20.0
